tests/__init__.py
tests/conftest.py
tests/test_gensim_topic_modelling.py
topicblob/__init__.py
topicblob/gensim_topic_modeling.py
topicblob/topic.py
topicblob-0.0.8.dist-info/LICENSE
topicblob-0.0.8.dist-info/METADATA
topicblob-0.0.8.dist-info/WHEEL
topicblob-0.0.8.dist-info/top_level.txt
topicblob-0.0.8.dist-info/RECORD
