Metadata-Version: 2.1
Name: topicblob
Version: 0.0.8
Summary: TopicBlob is a package to perform quick and easy topic modeling on text.
Home-page: https://github.com/banjtheman/TopicBlob
Author: Banjo Obayomi
Author-email: banjtheman@gmail.com
License: UNKNOWN
Keywords: python,topic modeling,gensim,nlp,spacy
Platform: UNKNOWN
Classifier: Development Status :: 5 - Production/Stable
Classifier: Intended Audience :: Developers
Classifier: Natural Language :: English
Classifier: Programming Language :: Python
Classifier: Programming Language :: Python :: 3
Classifier: Programming Language :: Python :: 3.6
Classifier: Programming Language :: Python :: 3.7
Classifier: Programming Language :: Python :: 3.8
Requires-Python: >3.6
Requires-Dist: nltk
Requires-Dist: rank-bm25
Requires-Dist: stop-words
Requires-Dist: pandas
Requires-Dist: wikipedia
Requires-Dist: python-Levenshtein
Requires-Dist: gensim
